praw/__init__.py
praw/config.py
praw/const.py
praw/endpoints.py
praw/exceptions.py
praw/objector.py
praw/praw.ini
praw/reddit.py
praw/images/PRAW logo.png
praw/models/__init__.py
praw/models/auth.py
praw/models/base.py
praw/models/comment_forest.py
praw/models/front.py
praw/models/helpers.py
praw/models/inbox.py
praw/models/mod_action.py
praw/models/mod_note.py
praw/models/mod_notes.py
praw/models/preferences.py
praw/models/redditors.py
praw/models/stylesheet.py
praw/models/subreddits.py
praw/models/trophy.py
praw/models/user.py
praw/models/util.py
praw/models/list/__init__.py
praw/models/list/base.py
praw/models/list/draft.py
praw/models/list/moderated.py
praw/models/list/redditor.py
praw/models/list/trophy.py
praw/models/listing/__init__.py
praw/models/listing/domain.py
praw/models/listing/generator.py
praw/models/listing/listing.py
praw/models/listing/mixins/__init__.py
praw/models/listing/mixins/base.py
praw/models/listing/mixins/gilded.py
praw/models/listing/mixins/redditor.py
praw/models/listing/mixins/rising.py
praw/models/listing/mixins/submission.py
praw/models/listing/mixins/subreddit.py
praw/models/reddit/__init__.py
praw/models/reddit/base.py
praw/models/reddit/collections.py
praw/models/reddit/comment.py
praw/models/reddit/draft.py
praw/models/reddit/emoji.py
praw/models/reddit/inline_media.py
praw/models/reddit/live.py
praw/models/reddit/message.py
praw/models/reddit/modmail.py
praw/models/reddit/more.py
praw/models/reddit/multi.py
praw/models/reddit/poll.py
praw/models/reddit/redditor.py
praw/models/reddit/removal_reasons.py
praw/models/reddit/rules.py
praw/models/reddit/submission.py
praw/models/reddit/subreddit.py
praw/models/reddit/user_subreddit.py
praw/models/reddit/widgets.py
praw/models/reddit/wikipage.py
praw/models/reddit/mixins/__init__.py
praw/models/reddit/mixins/editable.py
praw/models/reddit/mixins/fullname.py
praw/models/reddit/mixins/gildable.py
praw/models/reddit/mixins/inboxable.py
praw/models/reddit/mixins/inboxtoggleable.py
praw-7.7.1.dist-info/AUTHORS.rst
praw-7.7.1.dist-info/LICENSE.txt
praw-7.7.1.dist-info/METADATA
praw-7.7.1.dist-info/WHEEL
praw-7.7.1.dist-info/top_level.txt
praw-7.7.1.dist-info/RECORD
